fake_me_some/.DS_Store
fake_me_some/README.md
fake_me_some/__init__.py
fake_me_some/config.yaml
fake_me_some/fake_me_some.py
fake_me_some/faker_doc.txt
fake_me_some/provider.yml
fake_me_some/requirements.txt
fake_me_some/utils.py
fake_me_some-0.1.26.dist-info/AUTHORS.rst
fake_me_some-0.1.26.dist-info/LICENSE.txt
fake_me_some-0.1.26.dist-info/METADATA
fake_me_some-0.1.26.dist-info/WHEEL
fake_me_some-0.1.26.dist-info/entry_points.txt
fake_me_some-0.1.26.dist-info/top_level.txt
fake_me_some-0.1.26.dist-info/RECORD
