Metadata-Version: 2.1
Name: fake-me-some
Version: 0.1.26
Summary: utilily to fake some data to cvs, parquet or straight to a database!
Home-page: https://pyscaffold.org/
Author: Hung Nguyen
Author-email: hung135@hotmail.com
License: mit
Platform: any
Classifier: Development Status :: 4 - Beta
Classifier: Programming Language :: Python
Requires-Python: >=3.6
Requires-Dist: py-dbutils
Requires-Dist: pyyaml
Requires-Dist: pyarrow
Requires-Dist: faker
Requires-Dist: python-Levenshtein
Provides-Extra: testing
Requires-Dist: pytest ; extra == 'testing'
Requires-Dist: pytest-cov ; extra == 'testing'
